<?xml version="1.0" encoding="UTF-8" ?>
<!DOCTYPE tiles-definitions PUBLIC
       "-//Apache Software Foundation//DTD Tiles Configuration 3.0//EN"
       "http://tiles.apache.org/dtds/tiles-config_3_0.dtd">
<tiles-definitions>

	<definition name="common" template="/WEB-INF/layout/classic.jsp">
		<put-attribute name="footer" value="/WEB-INF/layout/footer.jsp" />
	</definition>

	<definition name="index" extends="common">
		<put-attribute name="title" value="Система автоматизации работы отдела кадров" />
		<put-attribute name="body" value="/WEB-INF/jsp/index.jsp" />
		<put-attribute name="current" value="index" />
	</definition>

	<definition name="users" extends="common">
		<put-attribute name="title"
			value="Users of Human Resources Management" />
		<put-attribute name="body" value="/WEB-INF/jsp/users.jsp" />
		<put-attribute name="current" value="users" />
	</definition>

	<definition name="user-detail" extends="common">
		<put-attribute name="title" value="User detail" />
		<put-attribute name="body" value="/WEB-INF/jsp/user-detail.jsp" />
		<put-attribute name="current" value="users" />
	</definition>
	
	<definition name="account" extends="common">
		<put-attribute name="title" value="User account" />
		<put-attribute name="body" value="/WEB-INF/jsp/user-account.jsp" />
		<put-attribute name="current" value="account" />
	</definition>

	<definition name="user-register" extends="common">
		<put-attribute name="title" value="User registration" />
		<put-attribute name="body" value="/WEB-INF/jsp/user-register.jsp" />
		<put-attribute name="current" value="register" />
	</definition>

	<definition name="login" extends="common">
		<put-attribute name="title" value="Авторизация" />
		<put-attribute name="body" value="/WEB-INF/jsp/login.jsp" />
		<put-attribute name="current" value="login" />
	</definition>
	
	
	<!-- my definitions: -->
	
	<definition name="edit-employee" extends="common">
		<put-attribute name="title" value="Редактирование записи о сотруднике" />
		<put-attribute name="body" value="/WEB-INF/jsp/edit-employee.jsp" />
		<put-attribute name="current" value="edit-employee" />
	</definition>
	
	<definition name="create-employee" extends="common">
		<put-attribute name="title" value="Создание записи о сотруднике" />
		<put-attribute name="body" value="/WEB-INF/jsp/create-employee.jsp" />
		<put-attribute name="current" value="create-employee" />
	</definition>
	
	<definition name="create-division" extends="common">
		<put-attribute name="title" value="Создание нового отдела" />
		<put-attribute name="body" value="/WEB-INF/jsp/create-division.jsp" />
		<put-attribute name="current" value="create-division" />
	</definition>
	
	<definition name="employee-detail" extends="common">
		<put-attribute name="title" value="Информация о сотруднике" />
		<put-attribute name="body" value="/WEB-INF/jsp/employee-detail.jsp" />
		<put-attribute name="current" value="employee-detail" />
	</definition>
	
	<definition name="divisions" extends="common">
		<put-attribute name="title" value="Отделы компании" />
		<put-attribute name="body" value="/WEB-INF/jsp/divisions.jsp" />
		<put-attribute name="current" value="divisions" />
	</definition>
	

</tiles-definitions>